{
    "$schema": "http://schema.management.azure.com/schemas/2015-01-01/deploymentTemplate.json#",
    "contentVersion": "1.0.0.0",
    "parameters": {
        "prefix": {
            "type": "string",
            "minLength": 1,
            "maxLength": 8,
            "metadata": {
                "description": "Prefix for each reasources."
            },
            "defaultValue": "mdisk"
        },
        "adminUserName": {
            "type": "string",
            "minLength": 1,
            "maxLength": 32,
            "metadata": {
                "description": "User name for administrator on the virtual machine."
            },
            "defaultValue": "vmadmin"
        },
        "adminPassword": {
            "type": "securestring",
            "metadata": {
                "description": "Password for administrator on the virtual machine."
            }
        }
    },
    "variables": {

        // Virtual Network

        "virtualNetworkName": "[concat(parameters('prefix'), '-vnet')]",
        "addressPrefix": "10.0.0.0/16",
        "subnetName": "default",
        "subnetAddressPrefix": "10.0.0.0/24",
        "virtualNetworkId": "[resourceId('Microsoft.Network/virtualNetworks', variables('virtualNetworkName'))]",
        "subnetId": "[concat(variables('virtualNetworkId'), '/subnets/', variables('subnetName'))]",

        // Virtual Machine

        "virtualMachineName": "[concat(parameters('prefix'), '-vm1')]",
        "virtualMachineSize": "Standard_DS1_v2",
        "virtualMachineOSDiskName": "[concat(variables('virtualMachineName'), '-osdisk')]",
        "virtualMachineDataDiskName1": "[concat(variables('virtualMachineName'), '-datadisk1')]",
        "virtualMachineId": "[resourceId('Microsoft.Compute/virtualMachines', variables('virtualMachineName'))]",

        // Network Interface

        "networkInterfaceName": "[concat(variables('virtualMachineName'), '-nic1')]",
        "networkInterfaceId": "[resourceId('Microsoft.Network/networkInterfaces', variables('networkInterfaceName'))]",

        // Public IP Address

        "publicIpAddressName": "[concat(variables('networkInterfaceName'), '-pip')]",
        "publicIpAddressId": "[resourceId('Microsoft.Network/publicIpAddresses', variables('publicIpAddressName'))]",

        // Network Security Group

        "networkSecurityGroupName": "[concat(parameters('prefix'), '-nsg')]",
        "networkSecurityGroupId": "[resourceId('Microsoft.Network/networkSecurityGroups', variables('networkSecurityGroupName'))]",

        // Diagnostics Storage Account

        "diagnosticsStorageAccountName": "[concat('diag', toLower(uniqueString(subscription().subscriptionId, resourceGroup().id)))]",
        "diagnosticsStorageAccountId": "[resourceId('Microsoft.Storage/storageAccounts', variables('diagnosticsStorageAccountName'))]",

        // Diagnostics VM Extension

        "diagnosticsExtensionName": "[concat(variables('virtualMachineName'), '/', 'Microsoft.Insights.VMDiagnosticsSettings')]"
    },
    "resources": [

        // Virtual Network

        {
            "name": "[variables('virtualNetworkName')]",
            "type": "Microsoft.Network/virtualNetworks",
            "apiVersion": "2018-08-01",
            "location": "[resourceGroup().location]",
            "dependsOn": [],
            "properties": {
                "addressSpace": {
                    "addressPrefixes": [
                        "[variables('addressPrefix')]"
                    ]
                },
                "subnets": [
                    {
                        "name": "[variables('subnetName')]",
                        "properties": {
                            "addressPrefix": "[variables('subnetAddressPrefix')]"
                        }
                    }
                ]
            },
            "tags": {}
        },

        // Virtual Machine

        {
            "name": "[variables('virtualMachineName')]",
            "type": "Microsoft.Compute/virtualMachines",
            "apiVersion": "2018-06-01",
            "location": "[resourceGroup().location]",
            "dependsOn": [
                "[variables('networkInterfaceId')]"
            ],
            "properties": {
                "hardwareProfile": {
                    "vmSize": "[variables('virtualMachineSize')]"
                },
                "storageProfile": {
                    "imageReference": {
                        "publisher": "MicrosoftWindowsServer",
                        "offer": "WindowsServer",
                        "sku": "2016-Datacenter-smalldisk",
                        "version": "latest"
                    },
                    "osDisk": {
                        "name": "[variables('virtualMachineOSDiskName')]",
                        "createOption": "FromImage",
                        "caching": "ReadWrite",
                        "managedDisk": {
                            "storageAccountType": "Standard_LRS"
                        }
                    },
                    "dataDisks": [
                        {
                            "name": "[variables('virtualMachineDataDiskName1')]",
                            "lun": 0,
                            "createOption": "Empty",
                            "diskSizeGB": 31,
                            "caching": "None",
                            "managedDisk":{
                                "storageAccountType": "Standard_LRS",
                            }
                        }
                    ]
                },
                "networkProfile": {
                    "networkInterfaces": [
                        {
                            "id": "[variables('networkInterfaceId')]",
                            "properties":{
                                "primary": true
                            }
                        }
                    ]
                },
                "osProfile": {
                    "computerName": "[variables('virtualMachineName')]",
                    "adminUsername": "[parameters('adminUserName')]",
                    "adminPassword": "[parameters('adminPassword')]",
                    "windowsConfiguration": {
                        "provisionVmAgent": true,
                        "timeZone": "Tokyo Standard Time"
                    }
                },
                "diagnosticsProfile": {
                    "bootDiagnostics": {
                        "enabled": true,
                        "storageUri": "[concat('https://', variables('diagnosticsStorageAccountName'), '.blob.core.windows.net/')]"
                    }
                }
            },
            "tags": {}
        },

        // Network Interface

        {
            "name": "[variables('networkInterfaceName')]",
            "type": "Microsoft.Network/networkInterfaces",
            "apiVersion": "2018-08-01",
            "location": "[resourceGroup().location]",
            "dependsOn": [
                "[variables('virtualNetworkId')]",
                "[variables('publicIpAddressId')]",
                "[variables('networkSecurityGroupId')]"
            ],
            "properties": {
                "ipConfigurations": [
                    {
                        "name": "ipconfig1",
                        "properties": {
                            "subnet": {
                                "id": "[variables('subnetId')]"
                            },
                            "privateIPAllocationMethod": "Dynamic",
                            "publicIPAddress": {
                                "id": "[variables('publicIpAddressId')]"
                            }
                        }
                    }
                ],
                "networkSecurityGroup": {
                    "id": "[variables('networkSecurityGroupId')]"
                }
            },
            "tags": {}
        },

        // Public IP Address

        {
            "name": "[variables('publicIpAddressName')]",
            "type": "Microsoft.Network/publicIpAddresses",
            "apiVersion": "2018-08-01",
            "location": "[resourceGroup().location]",
            "dependsOn": [],
            "properties": {
                "publicIpAllocationMethod": "Dynamic"
            },
            "sku": {
                "name": "Basic"
            },
            "tags": {}
        },

        // Network Security Group

        {
            "name": "[variables('networkSecurityGroupName')]",
            "type": "Microsoft.Network/networkSecurityGroups",
            "apiVersion": "2018-08-01",
            "location": "[resourceGroup().location]",
            "dependsOn": [],
            "properties": {
                "securityRules": [
                    {
                        "name": "RDP",
                        "properties": {
                            "priority": 1000,
                            "protocol": "Tcp",
                            "access": "Allow",
                            "direction": "Inbound",
                            "sourceAddressPrefix": "*",
                            "sourcePortRange": "*",
                            "destinationAddressPrefix": "*",
                            "destinationPortRange": "3389"
                        }
                    }
                ]
            },
            "tags": {}
        },

        // Diagnostics Storage Account 

        {
            "name": "[variables('diagnosticsStorageAccountName')]",
            "type": "Microsoft.Storage/storageAccounts",
            "apiVersion": "2018-07-01",
            "location": "[resourceGroup().location]",
            "dependsOn": [],
            "kind": "Storage",
            "sku": {
                "name": "Standard_LRS"
            },
            "properties": {},
            "tags": {}
        },

        // Diagnostics VM Extension

        {
            "name": "[variables('diagnosticsExtensionName')]",
            "type": "Microsoft.Compute/virtualMachines/extensions",
            "apiVersion": "2018-06-01",
            "location": "[resourceGroup().location]",
            "dependsOn": [
                "[variables('virtualMachineId')]",
                "[variables('diagnosticsStorageAccountId')]"
            ],
            "properties": {
                "publisher": "Microsoft.Azure.Diagnostics",
                "type": "IaaSDiagnostics",
                "typeHandlerVersion": "1.5",
                "autoUpgradeMinorVersion": true,
                "settings": {
                    "StorageAccount": "[variables('diagnosticsStorageAccountName')]",
                    "WadCfg": {
                        "DiagnosticMonitorConfiguration": {
                            "overallQuotaInMB": 5120,
                            "Metrics": {
                                "resourceId": "[variables('virtualMachineId')]",
                                "MetricAggregation": [
                                    {
                                        "scheduledTransferPeriod": "PT1H"
                                    },
                                    {
                                        "scheduledTransferPeriod": "PT1M"
                                    }
                                ]
                            },
                            "DiagnosticInfrastructureLogs": {
                                "scheduledTransferLogLevelFilter": "Error"
                            },
                            "PerformanceCounters": {
                                "scheduledTransferPeriod": "PT1M",
                                "PerformanceCounterConfiguration": [
                                    {
                                        "counterSpecifier": "\\Processor Information(_Total)\\% Processor Time",
                                        "sampleRate": "PT1M"
                                    },
                                    {
                                        "counterSpecifier": "\\Processor Information(_Total)\\% Privileged Time",
                                        "sampleRate": "PT1M"
                                    },
                                    {
                                        "counterSpecifier": "\\Processor Information(_Total)\\% User Time",
                                        "sampleRate": "PT1M"
                                    },
                                    {
                                        "counterSpecifier": "\\Processor Information(_Total)\\Processor Frequency",
                                        "sampleRate": "PT1M"
                                    },
                                    {
                                        "counterSpecifier": "\\System\\Processes",
                                        "sampleRate": "PT1M"
                                    },
                                    {
                                        "counterSpecifier": "\\Process(_Total)\\Thread Count",
                                        "sampleRate": "PT1M"
                                    },
                                    {
                                        "counterSpecifier": "\\Process(_Total)\\Handle Count",
                                        "sampleRate": "PT1M"
                                    },
                                    {
                                        "counterSpecifier": "\\System\\System Up Time",
                                        "sampleRate": "PT1M"
                                    },
                                    {
                                        "counterSpecifier": "\\System\\Context Switches/sec",
                                        "sampleRate": "PT1M"
                                    },
                                    {
                                        "counterSpecifier": "\\System\\Processor Queue Length",
                                        "sampleRate": "PT1M"
                                    },
                                    {
                                        "counterSpecifier": "\\Memory\\% Committed Bytes In Use",
                                        "sampleRate": "PT1M"
                                    },
                                    {
                                        "counterSpecifier": "\\Memory\\Available Bytes",
                                        "sampleRate": "PT1M"
                                    },
                                    {
                                        "counterSpecifier": "\\Memory\\Committed Bytes",
                                        "sampleRate": "PT1M"
                                    },
                                    {
                                        "counterSpecifier": "\\Memory\\Cache Bytes",
                                        "sampleRate": "PT1M"
                                    },
                                    {
                                        "counterSpecifier": "\\Memory\\Pool Paged Bytes",
                                        "sampleRate": "PT1M"
                                    },
                                    {
                                        "counterSpecifier": "\\Memory\\Pool Nonpaged Bytes",
                                        "sampleRate": "PT1M"
                                    },
                                    {
                                        "counterSpecifier": "\\Memory\\Pages/sec",
                                        "sampleRate": "PT1M"
                                    },
                                    {
                                        "counterSpecifier": "\\Memory\\Page Faults/sec",
                                        "sampleRate": "PT1M"
                                    },
                                    {
                                        "counterSpecifier": "\\Process(_Total)\\Working Set",
                                        "sampleRate": "PT1M"
                                    },
                                    {
                                        "counterSpecifier": "\\Process(_Total)\\Working Set - Private",
                                        "sampleRate": "PT1M"
                                    },
                                    {
                                        "counterSpecifier": "\\LogicalDisk(_Total)\\% Disk Time",
                                        "sampleRate": "PT1M"
                                    },
                                    {
                                        "counterSpecifier": "\\LogicalDisk(_Total)\\% Disk Read Time",
                                        "sampleRate": "PT1M"
                                    },
                                    {
                                        "counterSpecifier": "\\LogicalDisk(_Total)\\% Disk Write Time",
                                        "sampleRate": "PT1M"
                                    },
                                    {
                                        "counterSpecifier": "\\LogicalDisk(_Total)\\% Idle Time",
                                        "sampleRate": "PT1M"
                                    },
                                    {
                                        "counterSpecifier": "\\LogicalDisk(_Total)\\Disk Bytes/sec",
                                        "sampleRate": "PT1M"
                                    },
                                    {
                                        "counterSpecifier": "\\LogicalDisk(_Total)\\Disk Read Bytes/sec",
                                        "sampleRate": "PT1M"
                                    },
                                    {
                                        "counterSpecifier": "\\LogicalDisk(_Total)\\Disk Write Bytes/sec",
                                        "sampleRate": "PT1M"
                                    },
                                    {
                                        "counterSpecifier": "\\LogicalDisk(_Total)\\Disk Transfers/sec",
                                        "sampleRate": "PT1M"
                                    },
                                    {
                                        "counterSpecifier": "\\LogicalDisk(_Total)\\Disk Reads/sec",
                                        "sampleRate": "PT1M"
                                    },
                                    {
                                        "counterSpecifier": "\\LogicalDisk(_Total)\\Disk Writes/sec",
                                        "sampleRate": "PT1M"
                                    },
                                    {
                                        "counterSpecifier": "\\LogicalDisk(_Total)\\Avg. Disk sec/Transfer",
                                        "sampleRate": "PT1M"
                                    },
                                    {
                                        "counterSpecifier": "\\LogicalDisk(_Total)\\Avg. Disk sec/Read",
                                        "sampleRate": "PT1M"
                                    },
                                    {
                                        "counterSpecifier": "\\LogicalDisk(_Total)\\Avg. Disk sec/Write",
                                        "sampleRate": "PT1M"
                                    },
                                    {
                                        "counterSpecifier": "\\LogicalDisk(_Total)\\Avg. Disk Queue Length",
                                        "sampleRate": "PT1M"
                                    },
                                    {
                                        "counterSpecifier": "\\LogicalDisk(_Total)\\Avg. Disk Read Queue Length",
                                        "sampleRate": "PT1M"
                                    },
                                    {
                                        "counterSpecifier": "\\LogicalDisk(_Total)\\Avg. Disk Write Queue Length",
                                        "sampleRate": "PT1M"
                                    },
                                    {
                                        "counterSpecifier": "\\LogicalDisk(_Total)\\% Free Space",
                                        "sampleRate": "PT1M"
                                    },
                                    {
                                        "counterSpecifier": "\\LogicalDisk(_Total)\\Free Megabytes",
                                        "sampleRate": "PT1M"
                                    },
                                    {
                                        "counterSpecifier": "\\Network Interface(*)\\Bytes Total/sec",
                                        "sampleRate": "PT1M"
                                    },
                                    {
                                        "counterSpecifier": "\\Network Interface(*)\\Bytes Sent/sec",
                                        "sampleRate": "PT1M"
                                    },
                                    {
                                        "counterSpecifier": "\\Network Interface(*)\\Bytes Received/sec",
                                        "sampleRate": "PT1M"
                                    },
                                    {
                                        "counterSpecifier": "\\Network Interface(*)\\Packets/sec",
                                        "sampleRate": "PT1M"
                                    },
                                    {
                                        "counterSpecifier": "\\Network Interface(*)\\Packets Sent/sec",
                                        "sampleRate": "PT1M"
                                    },
                                    {
                                        "counterSpecifier": "\\Network Interface(*)\\Packets Received/sec",
                                        "sampleRate": "PT1M"
                                    },
                                    {
                                        "counterSpecifier": "\\Network Interface(*)\\Packets Outbound Errors",
                                        "sampleRate": "PT1M"
                                    },
                                    {
                                        "counterSpecifier": "\\Network Interface(*)\\Packets Received Errors",
                                        "sampleRate": "PT1M"
                                    }
                                ]
                            },
                            "WindowsEventLog": {
                                "scheduledTransferPeriod": "PT1M",
                                "DataSource": [
                                    {
                                        "name": "Application!*[System[(Level = 1 or Level = 2 or Level = 3)]]"
                                    },
                                    {
                                        "name": "Security!*[System[band(Keywords,4503599627370496)]]"
                                    },
                                    {
                                        "name": "System!*[System[(Level = 1 or Level = 2 or Level = 3)]]"
                                    }
                                ]
                            }
                        }
                    }
                },
                "protectedSettings": {
                    "storageAccountName": "[variables('diagnosticsStorageAccountName')]",
                    "storageAccountKey": "[listKeys(variables('diagnosticsStorageAccountId'), '2018-07-01').keys[0].value",
                    "storageAccountEndPoint": "https://core.windows.net/"
                }
            }
        }
    ],
    "outputs": {
    }
}
